pythonradex/LAMDA_file.py
pythonradex/__about__.py
pythonradex/__init__.py
pythonradex/atomic_transition.py
pythonradex/escape_probability.py
pythonradex/escape_probability_functions.py
pythonradex/flux.py
pythonradex/helpers.py
pythonradex/molecule.py
pythonradex/radiative_transfer.py
pythonradex/rate_equations.py
pythonradex-1.0.9.dist-info/METADATA
pythonradex-1.0.9.dist-info/WHEEL
pythonradex-1.0.9.dist-info/licenses/LICENSE.txt
pythonradex-1.0.9.dist-info/RECORD
